gisco_geodata/__init__.py
gisco_geodata/parser.py
gisco_geodata/theme.py
gisco_geodata/typing.py
gisco_geodata/utils.py
gisco_geodata-0.1.3.dist-info/licenses/LICENSE
gisco_geodata-0.1.3.dist-info/METADATA
gisco_geodata-0.1.3.dist-info/WHEEL
gisco_geodata-0.1.3.dist-info/top_level.txt
gisco_geodata-0.1.3.dist-info/RECORD
