Metadata-Version: 2.4
Name: gisco-geodata
Version: 0.1.3
Summary: GISCO Geodata is a Python package that provides access to the European Commission's GISCO geospatial data.
Author-email: Alex-Andrei Cuvuliuc <cuvuliucalexandrei@gmail.com>
License: MIT
Project-URL: Homepage, https://github.com/alecsandrei/gisco-geodata
Keywords: gisco-geodata
Classifier: Intended Audience :: Developers
Classifier: License :: OSI Approved :: MIT License
Classifier: Natural Language :: English
Classifier: Development Status :: 4 - Beta
Classifier: Programming Language :: Python :: 3.9
Classifier: Programming Language :: Python :: 3.10
Classifier: Programming Language :: Python :: 3.11
Classifier: Programming Language :: Python :: 3.12
Classifier: Programming Language :: Python :: 3.13
Classifier: Programming Language :: Python :: 3.14
Requires-Python: >=3.9
License-File: LICENSE
Requires-Dist: httpx
Requires-Dist: async-cache
Provides-Extra: all
Requires-Dist: gisco-geodata[dev,geo]; extra == "all"
Provides-Extra: dev
Requires-Dist: pytest; extra == "dev"
Requires-Dist: matplotlib; extra == "dev"
Requires-Dist: zest.releaser[recommended]; extra == "dev"
Requires-Dist: eurostat; extra == "dev"
Requires-Dist: geopandas; extra == "dev"
Requires-Dist: ruff; extra == "dev"
Requires-Dist: mypy; extra == "dev"
Requires-Dist: mapclassify>=2.8.1; extra == "dev"
Provides-Extra: geo
Requires-Dist: geopandas; extra == "geo"
Dynamic: license-file
